[{"addressLine":"3895 Church Street, Clarkston, GA 30021, USA","address1":"3895 Church Street","city":" Clarkston","state":"GA","zip":"30021","location":{"lat":33.8077297,"lng":-84.2399398},"locationType":"ROOFTOP"},{"addressLine":"1103 Bombay Lane, Roswell, GA 30076, USA","address1":"1103 Bombay Lane","city":" Roswell","state":"GA","zip":"30076","location":{"lat":34.053926,"lng":-84.33830909999999},"locationType":"ROOFTOP"},{"addressLine":"4675 Highway 27 North, Carrollton, GA","address1":"4675 Highway 27 North","city":" Carrollton","state":"GA","zip":null,"location":{"lat":33.67345299999999,"lng":-85.15016399999999},"locationType":"ROOFTOP"},{"addressLine":"1978 Mount Vernon Road, Atlanta, GA 30338, USA","address1":"1978 Mount Vernon Road","city":" Atlanta","state":"GA","zip":"30338","location":{"lat":33.9512386,"lng":-84.3205938},"locationType":"ROOFTOP"}]